Workbook

Sheet sales_data
A1: OrderID | B1: OrderDate | C1: Region | D1: Channel | E1: ProductCategory | F1: ProductName | G1: SalesAmount | H1: CostAmount | I1: Quantity | J1: CustomerID | K1: CustomerType | L1: IsRepeatPurchase | M1: Transaction Type
A2: ORD-10000 | B2: 45505 | C2: CA | D2: Online | E2: Laptops & Computers | F2: EliteDesk Mini PC | G2: 650 | H2: 450 | I2: 1 | J2: CUST-1178 | K2: Existing | L2: 1 | M2: Sale
A3: ORD-10001 | B3: 45505 | C3: TX | D3: Online | E3: Smart Home & IoT | F3: Smart Lighting Kit | G3: 240 | H3: 140 | I3: 2 | J3: CUST-2725 | K3: Existing | L3: 1 | M3: Sale
A4: ORD-10002 | B4: 45506 | C4: FL | D4: Partner | E4: Accessories & Power | F4: 10000mAh Power Bank | G4: 90 | H4: 40 | I4: 2 | J4: CUST-1162 | K4: Existing | L4: 1 | M4: Sale
A5: ORD-10003 | B5: 45506 | C5: TX | D5: Online | E5: Accessories & Power | F5: Mechanical Keyboard | G5: 220 | H5: 130 | I5: 2 | J5: CUST-1592 | K5: New | L5: 0 | M5: Sale
A6: ORD-10004 | B6: 45506 | C6: FL | D6: Direct | E6: Accessories & Power | F6: Mechanical Keyboard | G6: 220 | H6: 130 | I6: 2 | J6: CUST-2005 | K6: Existing | L6: 1 | M6: Sale
A7: ORD-10005 | B7: 45506 | C7: IL | D7: Online | E7: Smart Home & IoT | F7: Voice Assistant Hub | G7: 90 | H7: 55 | I7: 1 | J7: CUST-2193 | K7: New | L7: 0 | M7: Sale
A8: ORD-10006 | B8: 45506 | C8: IL | D8: Online | E8: Networking & Security | F8: IP Security Camera 4K | G8: 150 | H8: 90 | I8: 1 | J8: CUST-1300 | K8: New | L8: 0 | M8: Sale
A9: ORD-10007 | B9: 45507 | C9: WA | D9: Direct | E9: Laptops & Computers | F9: Workstation Tower | G9: 2400 | H9: 1700 | I9: 2 | J9: CUST-1373 | K9: New | L9: 0 | M9: Sale
A10: ORD-10008 | B10: 45507 | C10: TX | D10: Direct | E10: Laptops & Computers | F10: EliteDesk Mini PC | G10: 650 | H10: 450 | I10: 1 | J10: CUST-1707 | K10: New | L10: 0 | M10: Sale
A11: ORD-10009 | B11: 45507 | C11: TX | D11: Partner | E11: Networking & Security | F11: 24-Port PoE Switch | G11: 350 | H11: 220 | I11: 1 | J11: CUST-1202 | K11: New | L11: 0 | M11: Sale
A12: ORD-10010 | B12: 45507 | C12: NY | D12: Direct | E12: Smart Home & IoT | F12: Smart Thermostat Pro | G12: 660 | H12: 390 | I12: 3 | J12: CUST-1046 | K12: New | L12: 0 | M12: Sale
A13: ORD-10011 | B13: 45508 | C13: TX | D13: Partner | E13: Smart Home & IoT | F13: Voice Assistant Hub | G13: -180 | H13: -110 | I13: -2 | J13: CUST-1462 | K13: New | L13: 0 | M13: Return
... A2001: ORD-11999 | B2001: 46234 | C2001: NY | D2001: Online | E2001: Smart Home & IoT | F2001: Voice Assistant Hub | G2001: 86.67 | H2001: 52.97 | I2001: 1 | J2001: CUST-1332 | K2001: New | L2001: 0 | M2001: Sale

Sheet Pivot1 Sales
A3: Sum of SalesAmount | B3: Column Labels
B4: CA | E4: CA Total | F4: FL | I4: FL Total | J4: IL | M4: IL Total | N4: NY | Q4: NY Total | R4: TX | U4: TX Total | V4: WA | Y4: WA Total | Z4: Grand Total
A5: Row Labels | B5: Direct | C5: Online | D5: Partner | F5: Direct | G5: Online | H5: Partner | J5: Direct | K5: Online | L5: Partner | N5: Direct | O5: Online | P5: Partner | R5: Direct | S5: Online | T5: Partner | V5: Direct | W5: Online | X5: Partner
A6: 2024 | B6: 17135 | C6: 33310 | D6: 7505 | E6: 57950 | F6: 11040 | G6: 14080 | H6: 6880 | I6: 32000 | J6: 3845 | K6: 16580 | L6: 1700 | M6: 22125 | N6: 5860 | O6: 12970 | P6: 5835 | Q6: 24665 | R6: 21470 | S6: 31530 | T6: 11970 | U6: 64970 | V6: 11460 | W6: 10900 | X6: 4995 | Y6: 27355 | Z6: 229065
A7: 2025 | B7: 35660.19 | C7: 95474.07 | D7: 23579.36 | E7: 154713.62 | F7: 34405.23 | G7: 51739.34 | H7: 13811.18 | I7: 99955.75 | J7: 25760.55 | K7: 34216.22 | L7: 11512.01 | M7: 71488.78 | N7: 27566.91 | O7: 34331.88 | P7: 16842.92 | Q7: 78741.71 | R7: 15041.96 | S7: 41837.35 | T7: 13455.98 | U7: 70335.29 | V7: 17982.75 | W7: 27386.71 | X7: 13238.85 | Y7: 58608.31 | Z7: 533843.46
A8: 2026 | B8: 34457.63 | C8: 46659.47 | D8: 22289.59 | E8: 103406.69 | F8: 9654.51 | G8: 23276.76 | H8: 9471.54 | I8: 42402.81 | J8: 11065.34 | K8: 19833.85 | L8: 1589.02 | M8: 32488.21 | N8: 10266.04 | O8: 35444.76 | P8: 19395.68 | Q8: 65106.48 | R8: 21475.87 | S8: 33769.12 | T8: 15673.52 | U8: 70918.51 | V8: 16203.2 | W8: 14580.49 | X8: 6086.44 | Y8: 36870.13 | Z8: 351192.83
A9: Grand Total | B9: 87252.82 | C9: 175443.54 | D9: 53373.95 | E9: 316070.31 | F9: 55099.74 | G9: 89096.1 | H9: 30162.72 | I9: 174358.56 | J9: 40670.89 | K9: 70630.07 | L9: 14801.03 | M9: 126101.99 | N9: 43692.95 | O9: 82746.64 | P9: 42073.6 | Q9: 168513.19 | R9: 57987.83 | S9: 107136.47 | T9: 41099.5 | U9: 206223.8 | V9: 45645.95 | W9: 52867.2 | X9: 24320.29 | Y9: 122833.44 | Z9: 1114101.3

Sheet Pivot2 Products
A3: Row Labels | B3: Sum of SalesAmount | C3: Sum of CostAmount
A4: 10000mAh Power Bank | B4: 9548.78 | C4: 4243.78
A5: 24-Port PoE Switch | B5: 100337.06 | C5: 63069.28
A6: Dual-Band Wi-Fi 6 Router | B6: 43808.65 | C6: 26771.57
A7: EliteDesk Mini PC | B7: 200497.97 | C7: 138806.46
A8: IP Security Camera 4K | B8: 31501.45 | C8: 18900.6
A9: Mechanical Keyboard | B9: 26486.34 | C9: 15651.25
A10: ProBook 15.6" | B10: 264832.34 | C10: 186940.62
A11: Smart Lighting Kit | B11: 21819.05 | C11: 12727.64
A12: Smart Thermostat Pro | B12: 37955.78 | C12: 22428.52
A13: USB-C Triple Display Dock | B13: 32490.14 | C13: 19493.83
A14: Voice Assistant Hub | B14: 15520.58 | C14: 9484.88
A15: Workstation Tower | B15: 329303.15 | C15: 233256.65
A16: Grand Total | B16: 1114101.3 | C16: 751775.08

Sheet Pivot3 Repeat Rate
A3: Row Labels | B3: Sum of IsRepeatPurchase
A4: CA | B4: 182
A5: FL | B5: 90
A6: IL | B6: 61
A7: NY | B7: 90
A8: TX | B8: 119
A9: WA | B9: 56
A10: Grand Total | B10: 598

Sheet summary_metrics
A1: Metric | B1: PriorYear | C1: CurrentYear | D1: Change
A2: Total Sales Amount | B2: =SUMIFS(sales_data!G:G,sales_data!B:B,">=2024-08-01",sales_data!B:B,"<=2025-07-31") -> 551535 | C2: =SUMIFS(sales_data!G:G,sales_data!B:B,">=2025-08-01",sales_data!B:B,"<=2026-07-31") -> 562566.29 | D2: =(C2-B2)/B2 -> 0.02000107
A3: Total Cost Amount | B3: =SUMIFS(sales_data!H:H,sales_data!B:B,">=2024-08-01",sales_data!B:B,"<=2025-07-31") -> 371845 | C3: =SUMIFS(sales_data!H:H,sales_data!B:B,">=2025-08-01",sales_data!B:B,"<=2026-07-31") -> 379930.08 | D3: =(C3-B3)/B3 -> 0.021743146
A4: Gross Profit | B4: =B2-B3 -> 179690 | C4: =C2-C3 -> 182636.21 | D4: =(C4-B4)/B4 -> 0.016396071
A5: Gross Profit Margin | B5: =B4/B2 -> 0.32579981 | C5: =C4/C2 -> 0.32464834 | D5: =C5-B5 -> -0.0011514771
A7: Repeat Purchase Rate - California (CA) | B7: =AVERAGEIFS(sales_data!L:L,sales_data!C:C,"CA",sales_data!B:B,">=2024-08-01",sales_data!B:B,"<=2025-07-31") -> 0.34899329 | C7: =AVERAGEIFS(sales_data!L:L,sales_data!C:C,"CA",sales_data!B:B,">=2025-08-01",sales_data!B:B,"<=2026-07-31") -> 0.24920128 | D7: =C7-B7 -> -0.099792011
A8: Repeat Purchase Rate - Texas (TX) | B8: =AVERAGEIFS(sales_data!L:L,sales_data!C:C,"TX",sales_data!B:B,">=2024-08-01",sales_data!B:B,"<=2025-07-31") -> 0.34871795 | C8: =AVERAGEIFS(sales_data!L:L,sales_data!C:C,"TX",sales_data!B:B,">=2025-08-01",sales_data!B:B,"<=2026-07-31") -> 0.25123153 | D8: =C8-B8 -> -0.097486422
A9: Repeat Purchase Rate - New York (NY) | B9: =AVERAGEIFS(sales_data!L:L,sales_data!C:C,"NY",sales_data!B:B,">=2024-08-01",sales_data!B:B,"<=2025-07-31") -> 0.3028169 | C9: =AVERAGEIFS(sales_data!L:L,sales_data!C:C,"NY",sales_data!B:B,">=2025-08-01",sales_data!B:B,"<=2026-07-31") -> 0.29746835 | D9: =C9-B9 -> -0.005348547
A10: Repeat Purchase Rate - Florida (FL) | B10: =AVERAGEIFS(sales_data!L:L,sales_data!C:C,"FL",sales_data!B:B,">=2024-08-01",sales_data!B:B,"<=2025-07-31") -> 0.29746835 | C10: =AVERAGEIFS(sales_data!L:L,sales_data!C:C,"FL",sales_data!B:B,">=2025-08-01",sales_data!B:B,"<=2026-07-31") -> 0.3028169 | D10: =C10-B10 -> 0.005348547
A11: Repeat Purchase Rate - Illinois (IL) | B11: =AVERAGEIFS(sales_data!L:L,sales_data!C:C,"IL",sales_data!B:B,">=2024-08-01",sales_data!B:B,"<=2025-07-31") -> 0.29787234 | C11: =AVERAGEIFS(sales_data!L:L,sales_data!C:C,"IL",sales_data!B:B,">=2025-08-01",sales_data!B:B,"<=2026-07-31") -> 0.2972973 | D11: =C11-B11 -> -0.00057504313
A12: Repeat Purchase Rate - Washington (WA) | B12: =AVERAGEIFS(sales_data!L:L,sales_data!C:C,"WA",sales_data!B:B,">=2024-08-01",sales_data!B:B,"<=2025-07-31") -> 0.30107527 | C12: =AVERAGEIFS(sales_data!L:L,sales_data!C:C,"WA",sales_data!B:B,">=2025-08-01",sales_data!B:B,"<=2026-07-31") -> 0.30107527 | D12: =C12-B12 -> 0

Sheet hypothesis_testing
A1: Statistic | B1: H1_Online | C1: H1_Direct | D1: H2_CA_PY | E1: H2_CA_CY
A2: Sample Mean | B2: $634.25 | C2: $656.61 | D2: 34.90% | E2: 24.92%
A3: Sample StdDev | B3: $774.23 | C3: $761.27 | D3: 47.75% | E3: 43.32%
A4: Sample Size (N) | B4: 960 | C4: 543 | D4: 298 | E4: 313
A5: t-statistic | B5: -0.5436 | D5: 2.7014
A6: p-value | B6: 0.5868 | D6: 0.0071
A7: Significant? (alpha=0.05) | B7: No | D7: Yes

Sheet risk_matrix
A1: Risk | B1: Likelihood | C1: Impact | D1: Mitigation | E1: Owner
A2: Data Quality Risk (e.g., duplicate or missing OrderIDs) | B2: Medium | C2: High | D2: Implement automated database constraints and validation scripts before data load. | E2: Data Engineer
A3: Adoption Risk (e.g., business users continue using legacy reports) | B3: Medium | C3: Medium | D3: Conduct hands-on training sessions and deprecate old reporting tools. | E3: Product Manager
A4: Dependence on Manual Data Refresh | B4: High | C4: High | D4: Automate the data pipeline using scheduled ETL jobs (e.g., Airflow or dbt). | E4: BI Developer
A5: Inconsistent Regional Definitions | B5: Low | C5: Medium | D5: Establish a single source of truth for regional mapping in the data warehouse. | E5: Data Governance Lead

Sheet uat_tracker
A1: Scenario | B1: Acceptance Criteria | C1: Status | D1: Tester | E1: Date
A2: Verify that total sales in summary_metrics matches the sum of SalesAmount in sales_data | B2: The sum of SalesAmount in sales_data for PY and CY equals the sum of cells B2 and C2 on summary_metrics. | C2: Pass | D2: QA Analyst | E2: 8/18/2026
A3: Verify that California's repeat purchase rate correctly drops from ~35% to ~25% | B3: Cell B7 on summary_metrics shows ~35% and cell C7 shows ~25%. | C3: Pass | D3: QA Analyst | E3: 8/18/2026
A4: Verify that returns are correctly modeled as negative values | B4: Transactions with 'Transaction Type' = 'Return' have negative SalesAmount, CostAmount, and Quantity. | C4: Pass | D4: QA Analyst | E4: 8/18/2026
A5: Verify that Gross Profit is calculated correctly as Sales minus Cost | B5: Cell B4 equals B2-B3 and cell C4 equals C2-C3 on summary_metrics. | C5: Pass | D5: QA Analyst | E5: 8/18/2026
